LICENSE.rst
LICENSE_GPL.rst
MANIFEST.in
README.rst
setup.py
src/agx/__init__.py
src/agx.generator.plone.egg-info/PKG-INFO
src/agx.generator.plone.egg-info/SOURCES.txt
src/agx.generator.plone.egg-info/dependency_links.txt
src/agx.generator.plone.egg-info/entry_points.txt
src/agx.generator.plone.egg-info/namespace_packages.txt
src/agx.generator.plone.egg-info/not-zip-safe
src/agx.generator.plone.egg-info/requires.txt
src/agx.generator.plone.egg-info/top_level.txt
src/agx/generator/__init__.py
src/agx/generator/plone/__init__.py
src/agx/generator/plone/configure.zcml
src/agx/generator/plone/generator.rst
src/agx/generator/plone/gsgenerator.py
src/agx/generator/plone/profiles.py
src/agx/generator/plone/scope.py
src/agx/generator/plone/tests.py
src/agx/generator/plone/viewgenerator.py
src/agx/generator/plone/profiles/README.txt
src/agx/generator/plone/profiles/plone.profile.di
src/agx/generator/plone/profiles/plone.profile.notation
src/agx/generator/plone/profiles/plone.profile.uml
src/agx/generator/plone/resources/model_templates/plone_product/manifest.txt
src/agx/generator/plone/resources/model_templates/plone_product/model.di
src/agx/generator/plone/resources/model_templates/plone_product/model.notation
src/agx/generator/plone/resources/model_templates/plone_product/model.uml
src/agx/generator/plone/resources/model_templates/plone_product/model.uml.agx
src/agx/generator/plone/resources/model_templates/plone_product/uml_profiles/buildout.profile.uml
src/agx/generator/plone/resources/model_templates/plone_product/uml_profiles/plone.profile.uml
src/agx/generator/plone/resources/model_templates/plone_product/uml_profiles/pyegg.profile.uml
src/agx/generator/plone/resources/model_templates/plone_product/uml_profiles/zca.profile.uml
src/agx/generator/plone/templates/catalog.xml
src/agx/generator/plone/templates/controlpanel.xml
src/agx/generator/plone/templates/cssregistry.xml
src/agx/generator/plone/templates/factorytool.xml
src/agx/generator/plone/templates/import_steps.xml
src/agx/generator/plone/templates/jsregistry.xml
src/agx/generator/plone/templates/main.css.dtml
src/agx/generator/plone/templates/main.js.dtml
src/agx/generator/plone/templates/metadata.xml
src/agx/generator/plone/templates/portlets.xml
src/agx/generator/plone/templates/productname_marker.txt
src/agx/generator/plone/templates/rolemap.xml
